livesplit_analyser/ScrollLabel.py
livesplit_analyser/SplitResult.py
livesplit_analyser/__init__.py
livesplit_analyser/__version__.py
livesplit_analyser/gui.py
Livesplit_Analyser-1.0.6.dist-info/METADATA
Livesplit_Analyser-1.0.6.dist-info/WHEEL
Livesplit_Analyser-1.0.6.dist-info/entry_points.txt
Livesplit_Analyser-1.0.6.dist-info/top_level.txt
Livesplit_Analyser-1.0.6.dist-info/RECORD
