Metadata-Version: 2.1
Name: Livesplit-Analyser
Version: 1.0.6
Summary: Get statistical analysis from livesplit files
Home-page: https://https://github.com/IguanasInPyjamas/Livesplit-Analyser
Author: IguanasInPyjamas
Author-email: liquidmikerrs@gmail.com
License: UNKNOWN
Keywords: livesplit,statistics,graphs,playtime
Platform: UNKNOWN
Requires-Dist: PyQt5 (>=5.15.1)
Requires-Dist: matplotlib (>=3.3.3)
Requires-Dist: DateTime (>=4.3)
